{
    "gitbook": "3.x",
    "root": "docs",
    "title": "Glue",
    "author": "Maxime Fabre",
    "structure": {
        "summary": "README.md",
        "glossary": "GLOSSARY.md"
    },
    "plugins": [
        "edit-link",
        "github",
        "anchors",
        "prism",
        "-highlight"
    ],
    "styles": {
      "website": "styles.css"
    },
    "pluginsConfig": {
        "edit-link": {
            "base": "https://github.com/madewithlove/glue/tree/develop",
            "label": "Edit This Page"
        },
        "github": {
            "url": "https://github.com/madewithlove/glue"
        }
    }
}
